{
	"name": "Dataflow",
	"properties": {
		"type": "MappingDataFlow",
		"typeProperties": {
			"sources": [
				{
					"dataset": {
						"referenceName": "Dataset",
						"type": "DatasetReference"
					},
					"name": "source1"
				}
			],
			"sinks": [
				{
					"dataset": {
						"referenceName": "AzureSynapseAnalyticsCustomer",
						"type": "DatasetReference"
					},
					"name": "sink1"
				}
			],
			"transformations": [],
			"script": "source(allowSchemaDrift: true,\n\tvalidateSchema: false,\n\tignoreNoFilesFound: false) ~> source1\nsource1 sink(allowSchemaDrift: true,\n\tvalidateSchema: false,\n\tdeletable:false,\n\tinsertable:true,\n\tupdateable:false,\n\tupsertable:false,\n\tformat: 'table',\n\tstaged: true,\n\tskipDuplicateMapInputs: true,\n\tskipDuplicateMapOutputs: true) ~> sink1"
		}
	}
}